app/YouTubeAPICalls.py
app/__init__.py
app/config.py
app/database_control.py
app/models.py
app/movieTitles.txt
app/routes.py
app/service1.pkl
app/videoCaptions.py
app/api/__init__.py
app/api/auth.py
app/api/controllers.py
app/api/errors.py
app/api/service1.pkl
app/api/tokens.py
app/api/utils.py
app/api/videos.py
app/api/webservice.py
app/static/control.js
app/static/login.js
app/static/style.css
app/templates/control_page.html
app/templates/login.html
YTReviewsAPI-0.2.0.dist-info/METADATA
YTReviewsAPI-0.2.0.dist-info/WHEEL
YTReviewsAPI-0.2.0.dist-info/top_level.txt
YTReviewsAPI-0.2.0.dist-info/RECORD
