Metadata-Version: 2.1
Name: YTReviewsAPI
Version: 0.2.0
Summary: UNKNOWN
Home-page: UNKNOWN
Author: Porter Hunley
Author-email: porterhunley@gatech.edu
License: MIT
Platform: UNKNOWN
Requires-Dist: flask
